openpgx/__init__.py
openpgx/__main__.py
openpgx/cpic.py
openpgx/dpwg.py
openpgx/dpwg.sh
openpgx/fda.py
openpgx/helpers.py
openpgx/openpgx.py
openpgx-0.0.1.dist-info/LICENSE
openpgx-0.0.1.dist-info/WHEEL
openpgx-0.0.1.dist-info/METADATA
openpgx-0.0.1.dist-info/RECORD
